crlfi/__init__.py
crlfi/main.py
crlfi/includes/__init__.py
crlfi/includes/bot.py
crlfi/includes/crlfi.py
crlfi/includes/filereader.py
crlfi/includes/writefile.py
crlfi/utils/__init__.py
crlfi/utils/configure.py
crlfi/utils/helper.py
includes/__init__.py
includes/bot.py
includes/crlfi.py
includes/filereader.py
includes/writefile.py
utils/__init__.py
utils/configure.py
utils/helper.py
crlfihunter-0.0.2.dist-info/LICENSE
crlfihunter-0.0.2.dist-info/METADATA
crlfihunter-0.0.2.dist-info/WHEEL
crlfihunter-0.0.2.dist-info/entry_points.txt
crlfihunter-0.0.2.dist-info/top_level.txt
crlfihunter-0.0.2.dist-info/RECORD
