Metadata-Version: 2.1
Name: crlfihunter
Version: 0.0.2
Author: @karthithehacker
Author-email: <contact@karthithehacker.com>
Keywords: python,crlf,crlfi,injection,crlfinjection
Classifier: Development Status :: 1 - Planning
Classifier: Intended Audience :: Developers
Classifier: Programming Language :: Python :: 3
Classifier: Operating System :: Unix
Classifier: Operating System :: MacOS :: MacOS X
Classifier: Operating System :: Microsoft :: Windows
License-File: LICENSE
Requires-Dist: urllib3
Requires-Dist: requests
Requires-Dist: click
Requires-Dist: pyyaml
